fds/__init__.py
fds/sdk/__init__.py
fds/sdk/BestExecutionAnalyticsforSmarterTradingBEAST/__init__.py
fds/sdk/BestExecutionAnalyticsforSmarterTradingBEAST/api_client.py
fds/sdk/BestExecutionAnalyticsforSmarterTradingBEAST/configuration.py
fds/sdk/BestExecutionAnalyticsforSmarterTradingBEAST/exceptions.py
fds/sdk/BestExecutionAnalyticsforSmarterTradingBEAST/model_utils.py
fds/sdk/BestExecutionAnalyticsforSmarterTradingBEAST/rest.py
fds/sdk/BestExecutionAnalyticsforSmarterTradingBEAST/api/__init__.py
fds/sdk/BestExecutionAnalyticsforSmarterTradingBEAST/api/liquidity_analytics_api.py
fds/sdk/BestExecutionAnalyticsforSmarterTradingBEAST/api/market_impact_api.py
fds/sdk/BestExecutionAnalyticsforSmarterTradingBEAST/api/order_details_api.py
fds/sdk/BestExecutionAnalyticsforSmarterTradingBEAST/api/order_search_api.py
fds/sdk/BestExecutionAnalyticsforSmarterTradingBEAST/api/outliers_api.py
fds/sdk/BestExecutionAnalyticsforSmarterTradingBEAST/api/reports_api.py
fds/sdk/BestExecutionAnalyticsforSmarterTradingBEAST/apis/__init__.py
fds/sdk/BestExecutionAnalyticsforSmarterTradingBEAST/model/__init__.py
fds/sdk/BestExecutionAnalyticsforSmarterTradingBEAST/model/aggregate_market_impact.py
fds/sdk/BestExecutionAnalyticsforSmarterTradingBEAST/model/cost_impact_response_root_v3.py
fds/sdk/BestExecutionAnalyticsforSmarterTradingBEAST/model/cost_impact_v3.py
fds/sdk/BestExecutionAnalyticsforSmarterTradingBEAST/model/error.py
fds/sdk/BestExecutionAnalyticsforSmarterTradingBEAST/model/error_response.py
fds/sdk/BestExecutionAnalyticsforSmarterTradingBEAST/model/field_values_response.py
fds/sdk/BestExecutionAnalyticsforSmarterTradingBEAST/model/field_values_response_root.py
fds/sdk/BestExecutionAnalyticsforSmarterTradingBEAST/model/index_etf.py
fds/sdk/BestExecutionAnalyticsforSmarterTradingBEAST/model/index_etf_response.py
fds/sdk/BestExecutionAnalyticsforSmarterTradingBEAST/model/index_etf_response_root.py
fds/sdk/BestExecutionAnalyticsforSmarterTradingBEAST/model/intra_order_stat.py
fds_sdk_bestexecutionanalyticsforsmartertradingbeast-0.3.0.dist-info/licenses/LICENSE
fds_sdk_bestexecutionanalyticsforsmartertradingbeast-0.3.0.dist-info/METADATA
fds_sdk_bestexecutionanalyticsforsmartertradingbeast-0.3.0.dist-info/WHEEL
fds_sdk_bestexecutionanalyticsforsmartertradingbeast-0.3.0.dist-info/top_level.txt
fds_sdk_bestexecutionanalyticsforsmartertradingbeast-0.3.0.dist-info/RECORD
